<?xml version="1.0" encoding="utf-8"?>
<!-- This document contains U.S. state names and standard abbreviations -->
<states xmlns="urn:states-schema">
  <state abbrev="" name="&lt;None Selected&gt;" />
  <state abbrev="AL" name="Alabama" />
  <state abbrev="AK" name="Alaska" />
  <state abbrev="AZ" name="Arizona" />
  <state abbrev="AK" name="Arkansas" />
  <state abbrev="CA" name="California" />
  <state abbrev="CO" name="Colorado" />
  <state abbrev="CT" name="Connecticut" />
  <state abbrev="DE" name="Delaware" />
  <state abbrev="DC" name="District of Columbia" />
  <state abbrev="FL" name="Florida" />
  <state abbrev="GA" name="Georgia" />
  <state abbrev="HI" name="Hawaii" />
  <state abbrev="ID" name="Idaho" />
  <state abbrev="IL" name="Illinois" />
  <state abbrev="IN" name="Indiana" />
  <state abbrev="IA" name="Iowa" />
  <state abbrev="KS" name="Kansas" />
  <state abbrev="KY" name="Kentucky" />
  <state abbrev="LA" name="Louisiana" />
  <state abbrev="ME" name="Maine" />
  <state abbrev="MD" name="Maryland" />
  <state abbrev="MA" name="Massachusetts" />
  <state abbrev="MI" name="Michigan" />
  <state abbrev="MN" name="Minnesota" />
  <state abbrev="MS" name="Mississippi" />
  <state abbrev="MO" name="Missouri" />
  <state abbrev="MT" name="Montana" />
  <state abbrev="NE" name="Nebraska" />
  <state abbrev="NV" name="Nevada" />
  <state abbrev="NH" name="New Hampshire" />
  <state abbrev="NJ" name="New Jersey" />
  <state abbrev="NM" name="New Mexico" />
  <state abbrev="NY" name="New York" />
  <state abbrev="NC" name="North Carolina" />
  <state abbrev="ND" name="North Dakota" />
  <state abbrev="OH" name="Ohio" />
  <state abbrev="OK" name="Oklahoma" />
  <state abbrev="OR" name="Oregon" />
  <state abbrev="PA" name="Pennsylvania" />
  <state abbrev="RI" name="Rhode Island" />
  <state abbrev="SC" name="South Carolina" />
  <state abbrev="SD" name="South Dakota" />
  <state abbrev="TN" name="Tennessee" />
  <state abbrev="TX" name="Texas" />
  <state abbrev="UT" name="Utah" />
  <state abbrev="VT" name="Vermont" />
  <state abbrev="VA" name="Virginia" />
  <state abbrev="WA" name="Washington" />
  <state abbrev="WV" name="West Virginia" />
  <state abbrev="WI" name="Wisconsin" />
  <state abbrev="WY" name="Wyoming" />
</states>